
{ 
    "posts": [
	{
		"name": "Fulton Dillon",
		"text": "a purus. Duis elementum, dui quis accumsan convallis, ante lectus"
	},
	{
		"name": "Bert Nguyen",
		"text": "dictum eleifend, nunc risus varius orci, in consequat enim diam"
	},
	{
		"name": "Rama Torres",
		"text": "at risus. Nunc ac sem ut dolor dapibus gravida. Aliquam"
	},
	{
		"name": "Talon Frost",
		"text": "ullamcorper. Duis cursus, diam at pretium aliquet, metus urna convallis"
	},
	{
		"name": "Roth Byers",
		"text": "vel nisl. Quisque fringilla euismod enim. Etiam gravida molestie arcu."
	}
]  }

